umipy/__init__.py
umipy/api.py
umipy/bech32.py
umipy/constants.py
umipy/enums.py
umipy/exceptions.py
umipy/generate_wallet.py
umipy/helpers.py
umipy/models.py
umipy/py.typed
umipy/transfer.py
umipy-2.2.2.dist-info/METADATA
umipy-2.2.2.dist-info/WHEEL
umipy-2.2.2.dist-info/RECORD
