Metadata-Version: 2.4
Name: umipy
Version: 2.2.2
Summary: api wrapper for umi.top crypto
Project-URL: Repository, https://github.com/kesha1225/PyUmi
Author: kesha1225
License-Expression: MIT
Keywords: api,crypto,umi,wrapper
Classifier: Development Status :: 5 - Production/Stable
Classifier: Intended Audience :: Developers
Classifier: License :: OSI Approved :: MIT License
Classifier: Programming Language :: Python :: 3.12
Classifier: Topic :: Software Development :: Libraries :: Python Modules
Requires-Python: ~=3.12
Requires-Dist: aiohttp<4,>=3.10.3
Requires-Dist: mnemonic<0.22,>=0.21
Requires-Dist: pydantic<3,>=2.4.2
Requires-Dist: pynacl<2,>=1.5.0
